Cryptodome/__init__.py
Cryptodome/__init__.pyi
Cryptodome/py.typed
Cryptodome/Cipher/AES.py
Cryptodome/Cipher/AES.pyi
Cryptodome/Cipher/ARC2.py
Cryptodome/Cipher/ARC2.pyi
Cryptodome/Cipher/ARC4.py
Cryptodome/Cipher/ARC4.pyi
Cryptodome/Cipher/Blowfish.py
Cryptodome/Cipher/Blowfish.pyi
Cryptodome/Cipher/CAST.py
Cryptodome/Cipher/CAST.pyi
Cryptodome/Cipher/ChaCha20.py
Cryptodome/Cipher/ChaCha20.pyi
Cryptodome/Cipher/ChaCha20_Poly1305.py
Cryptodome/Cipher/ChaCha20_Poly1305.pyi
Cryptodome/Cipher/DES.py
Cryptodome/Cipher/DES.pyi
Cryptodome/Cipher/DES3.py
Cryptodome/Cipher/DES3.pyi
Cryptodome/Cipher/PKCS1_OAEP.py
Cryptodome/Cipher/PKCS1_OAEP.pyi
Cryptodome/Cipher/PKCS1_v1_5.py
Cryptodome/Cipher/PKCS1_v1_5.pyi
Cryptodome/Cipher/Salsa20.py
Cryptodome/Cipher/Salsa20.pyi
Cryptodome/Cipher/_ARC4.pypy39-pp73-win_amd64.pyd
Cryptodome/Cipher/_EKSBlowfish.py
Cryptodome/Cipher/_EKSBlowfish.pyi
Cryptodome/Cipher/_Salsa20.pypy39-pp73-win_amd64.pyd
Cryptodome/Cipher/__init__.py
Cryptodome/Cipher/__init__.pyi
Cryptodome/Cipher/_chacha20.pypy39-pp73-win_amd64.pyd
Cryptodome/Cipher/_mode_cbc.py
Cryptodome/Cipher/_mode_cbc.pyi
Cryptodome/Cipher/_mode_ccm.py
Cryptodome/Cipher/_mode_ccm.pyi
Cryptodome/Cipher/_mode_cfb.py
Cryptodome/Cipher/_mode_cfb.pyi
Cryptodome/Cipher/_mode_ctr.py
Cryptodome/Cipher/_mode_ctr.pyi
Cryptodome/Cipher/_mode_eax.py
Cryptodome/Cipher/_mode_eax.pyi
Cryptodome/Cipher/_mode_ecb.py
Cryptodome/Cipher/_mode_ecb.pyi
Cryptodome/Cipher/_mode_gcm.py
Cryptodome/Cipher/_mode_gcm.pyi
Cryptodome/Cipher/_mode_kw.py
Cryptodome/Cipher/_mode_kwp.py
Cryptodome/Cipher/_mode_ocb.py
Cryptodome/Cipher/_mode_ocb.pyi
Cryptodome/Cipher/_mode_ofb.py
Cryptodome/Cipher/_mode_ofb.pyi
Cryptodome/Cipher/_mode_openpgp.py
Cryptodome/Cipher/_mode_openpgp.pyi
Cryptodome/Cipher/_mode_siv.py
Cryptodome/Cipher/_mode_siv.pyi
Cryptodome/Cipher/_pkcs1_decode.pypy39-pp73-win_amd64.pyd
Cryptodome/Cipher/_pkcs1_oaep_decode.py
Cryptodome/Cipher/_raw_aes.pypy39-pp73-win_amd64.pyd
pycryptodomex-3.23.0.dist-info/licenses/AUTHORS.rst
pycryptodomex-3.23.0.dist-info/licenses/LICENSE.rst
pycryptodomex-3.23.0.dist-info/METADATA
pycryptodomex-3.23.0.dist-info/WHEEL
pycryptodomex-3.23.0.dist-info/top_level.txt
pycryptodomex-3.23.0.dist-info/RECORD
